example/chat_async.py
local_broadcast/__init__.py
local_broadcast-0.0.7.dist-info/LICENSE
local_broadcast-0.0.7.dist-info/METADATA
local_broadcast-0.0.7.dist-info/WHEEL
local_broadcast-0.0.7.dist-info/top_level.txt
local_broadcast-0.0.7.dist-info/RECORD
